threatstate/__init__.py
threatstate-0.0.1.dist-info/METADATA
threatstate-0.0.1.dist-info/WHEEL
threatstate-0.0.1.dist-info/top_level.txt
threatstate-0.0.1.dist-info/RECORD
