Metadata-Version: 2.1
Name: threatstate
Version: 0.0.1
Summary: Threatstate application
Home-page: https://github.com/threatstate/threatstate
Author: threatstate
License: Apache-2.0
Platform: UNKNOWN
